gmdapi_python/__init__.py
gmdapi_python/gmdapi_python.py
gmdapi_python-1.0.0b2.dist-info/LICENSE.txt
gmdapi_python-1.0.0b2.dist-info/METADATA
gmdapi_python-1.0.0b2.dist-info/WHEEL
gmdapi_python-1.0.0b2.dist-info/top_level.txt
gmdapi_python-1.0.0b2.dist-info/RECORD
