Metadata-Version: 2.1
Name: gmdapi-python
Version: 1.0.0b2
Summary: GDAPI is a simple Python Geometry Dash API module.
Home-page: https://github.com/Xytriza/gmdapi-python
Author: Xytriza
Author-email: cryfxreal@gmail.com
Classifier: Programming Language :: Python :: 3
Classifier: License :: OSI Approved :: MIT License
Classifier: Operating System :: OS Independent
Requires-Python: >=3.11
License-File: LICENSE.txt
Requires-Dist: requests
